nextcord/ext/menus/__init__.py
nextcord/ext/menus/constants.py
nextcord/ext/menus/exceptions.py
nextcord/ext/menus/menu_pages.py
nextcord/ext/menus/menus.py
nextcord/ext/menus/page_source.py
nextcord/ext/menus/utils.py
nextcord_ext_menus-1.5.7.dist-info/LICENSE
nextcord_ext_menus-1.5.7.dist-info/METADATA
nextcord_ext_menus-1.5.7.dist-info/WHEEL
nextcord_ext_menus-1.5.7.dist-info/top_level.txt
nextcord_ext_menus-1.5.7.dist-info/RECORD
