Metadata-Version: 2.1
Name: nextcord-ext-menus
Version: 1.5.7
Summary: An extension module to make reaction and button component menus with nextcord
Home-page: https://github.com/nextcord/nextcord-ext-menus
Author: Nextcord Developers
License: MIT
Project-URL: Bug Tracker, https://github.com/nextcord/nextcord-ext-menus/issues
Requires-Python: >=3.8.0
Provides-Extra: docs
License-File: LICENSE
